CHANGELOG.md
LICENSE.md
MANIFEST.in
README.md
setup.py
easeMaker/__init__.py
easeMaker/_api.py
easeMaker/_clearJunks.py
easeMaker/_date.py
easeMaker/_file_manager.py
easeMaker/_gameEngine.py
easeMaker/_json.py
easeMaker/_maths.py
easeMaker/_path.py
easeMaker/_system.py
easeMaker/_time.py
easeMaker/_user.py
easeMaker/_util.py
easeMaker/test.py
easeMaker.egg-info/PKG-INFO
easeMaker.egg-info/SOURCES.txt
easeMaker.egg-info/dependency_links.txt
easeMaker.egg-info/top_level.txt